CHANGES.rst
CONTRIBUTORS.rst
LICENSE.txt
MANIFEST.in
README.rst
setup.cfg
setup.py
docs/source/CHANGES.rst
docs/source/CONTRIBUTORS.rst
docs/source/README.rst
docs/source/index.rst
docs/source/modules.rst
docs/source/owncloud.owncloud.rst
docs/source/owncloud.rst
owncloud/__init__.py
owncloud/owncloud.py
owncloud/test/__init__.py
owncloud/test/config.py
owncloud/test/test.py
pyocclient.egg-info/PKG-INFO
pyocclient.egg-info/SOURCES.txt
pyocclient.egg-info/dependency_links.txt
pyocclient.egg-info/requires.txt
pyocclient.egg-info/top_level.txt