Metadata-Version: 1.1
Name: pyocclient
Version: 0.5
Summary: Python client library for ownCloud
Home-page: https://github.com/owncloud/pyocclient/
Author: Vincent Petry
Author-email: pvince81@owncloud.com
License: LICENSE.txt
Platform: UNKNOWN
Classifier: Programming Language :: Python
Classifier: Programming Language :: Python :: 2
Classifier: Programming Language :: Python :: 3
Classifier: Development Status :: 3 - Alpha
Classifier: Environment :: Web Environment
Classifier: Intended Audience :: Developers
Classifier: Topic :: Internet :: WWW/HTTP
Classifier: Topic :: Software Development :: Libraries :: Python Modules
Classifier: License :: OSI Approved :: MIT License
